fastapi_starter/__init__.py
fastapi_starter/cli.py
fastapi_starter-0.1.3.dist-info/LICENCE
fastapi_starter-0.1.3.dist-info/METADATA
fastapi_starter-0.1.3.dist-info/WHEEL
fastapi_starter-0.1.3.dist-info/entry_points.txt
fastapi_starter-0.1.3.dist-info/top_level.txt
fastapi_starter-0.1.3.dist-info/RECORD
