Metadata-Version: 2.1
Name: fastapi_starter
Version: 0.1.3
Summary: A biblioteca fastapi_starter é uma ferramenta projetada para facilitar a criação rápida e eficiente de projetos baseados no framework FastAPI. Ele automatiza a criação da estrutura básica do projeto, incluindo diretórios, arquivos de configuração e rotas iniciais, além de instalar automaticamente todas as dependências necessárias. Com o fastapi_starter, os desenvolvedores podem iniciar novos projetos FastAPI com apenas alguns comandos, economizando tempo e esforço.
Author: Jose Guilherme Lins Filho
Author-email: zeguilhermelins@hotmail.com
License: MIT License
Keywords: fastapi starter
Requires-Python: >=3.6
License-File: LICENCE
Requires-Dist: annotated-types
Requires-Dist: anyio
Requires-Dist: certifi
Requires-Dist: click
Requires-Dist: colorama
Requires-Dist: dnspython
Requires-Dist: email-validator
Requires-Dist: fastapi
Requires-Dist: fastapi-cli
Requires-Dist: greenlet
Requires-Dist: h11
Requires-Dist: httpcore
Requires-Dist: httptools
Requires-Dist: httpx
Requires-Dist: idna
Requires-Dist: Jinja2
Requires-Dist: markdown-it-py
Requires-Dist: MarkupSafe
Requires-Dist: mdurl
Requires-Dist: orjson
Requires-Dist: pydantic
Requires-Dist: pydantic-core
Requires-Dist: Pygments
Requires-Dist: python-dotenv
Requires-Dist: python-multipart
Requires-Dist: PyYAML
Requires-Dist: rich
Requires-Dist: shellingham
Requires-Dist: sniffio
Requires-Dist: SQLAlchemy
Requires-Dist: starlette
Requires-Dist: typer
Requires-Dist: typing-extensions
Requires-Dist: ujson
Requires-Dist: uvicorn
Requires-Dist: watchfiles
Requires-Dist: websockets
